{
  "name": "Nellie Evans",
  "age": 49,
  "address": {
    "street": "Sabuh Point",
    "city": "Basacdun",
    "state": "KY",
    "zip": "94596"
  },
  "contact": {
    "phone": "(602) 950-9851",
    "servicePhone": "800417513"
  },
  "birthday": "2000-11-21T09:56:26.383Z",
  "ip": "108.67.125.89",
  "foo": "bar",
  "profile": {
    "about": "Vita dorje dirdog divup cakre fuk zodceroj pe ni cavjaf ji ertusib oso nafur miterjob ijiacri kimfijuh. Fun vacov agwofdim pujmivna ze iwda ku vapokimaz jo vuhzim tujaj jase vofaj. Husid apa sav bufco sevzaz ri zavipru bom vugiwo dip danla cokovuk nucvaro ugu gehit fobfib bij. Hugukofe ji kipu le owuvnut jafpupe woba owasuw omzemi gerle lefwup nal. Pasojasi mawaka lowila tonis wi if neli lune puvmoozu fehifu losvab car as.",
    "bio": "Tuj dimem dak ifvogin hi nocub fi jomzozre sas conelu tel wofisus nes tamza afuolwih. Me ejkik ruj fulno wurdop koh cilebe zeori na garve ki ditmagic tehnosmo. Havfafses kos zuspagi bagvul kacaz juzekla nirwehwe ebi tekzuk kag sougopec movilti ziwabuzi poj bano juzonagim."
  },
  "apiKey": "41fcaf28be071124874ad5262bd8cb8c33a1e4924cd1e74422a920fd44657f22",
  "currency": {
    "code": "GHS",
    "name": "Ghana Cedi"
  }
}