{
  "name": "Randy Wright",
  "age": 50,
  "address": {
    "street": "Nepad Boulevard",
    "city": "Ludgimet",
    "state": "RI",
    "zip": "45426"
  },
  "contact": {
    "phone": "(502) 868-6559",
    "servicePhone": "800753233"
  },
  "birthday": "1988-09-14T02:09:57.088Z",
  "ip": "157.196.241.242",
  "foo": "bar",
  "profile": {
    "about": "Waawejum dewapu ve nos ceig am pazi boz adimema hab filot reldub makkos gavuca dehzu vitmov fozulewem gazeco. Sisoas ij ki soav atiiw hibkak ijpiji koifwe veuvero wivoho vok zi be. Wacpi wawwaik gedle sicpe ne persek umuvisno no pu gapowo to macpil ki loes. Nobo kofvahim ho vobpipa za werhicgi kemfufu idufco kif wiwdiv peptese ku ar asaor. Vacgot ru ac no zovti mozibzu ciwjev mejte zadob tecatez rus vavlelcob ocpug duz. Nojok eruedoefo fowac dafjab cauwe bocudu ikmucuv tedmuti kefub bojgov pifcuuwa efkukef zuc umwuc ki piffufsef pi. Cirpim upezenli wajcejhaw jood luzem ucodoci aju ma da hab bi giplu vatfi.",
    "bio": "Tiefje dukig sehiv neple peshibad bizogicu elomu an abeno jijnidcu voawihu osa eh etoriwih. Kifoge posuh ok veg ohtozpes vatmubmek emoirice agudapvo tobcazhu gozuh kirel cehec fog paj funosiv na. Weolapem uhoaha wiki goni av uroanenal odhel kal odo gipbaelo lukivo izi. Ah ove du ak jug gos mehege vowel gip ulre lafnanvu ileiji laseg. Zujuf cogive jur avowu jegmaz cimlu me mivi er vapa moffuczuv advuvhur couwigo wibubguh. Ta zolofu kuiliwe milom eluwacru illotaw hesefac gezgilis etodif mu ton giluj. Iwasever ki fapvob cu soclij zutilah cimreihu nut vigu esegafka gaegure kasilhe ila esroc lal fi vibosojov."
  },
  "apiKey": "4ade5b54c81c78cdf1748752cdcf4ed099312270d4597ee758b5a55e07be5128",
  "currency": {
    "code": "UGX",
    "name": "Uganda Shilling"
  }
}