{
  "name": "Lee Wong",
  "age": 64,
  "address": {
    "street": "Soaf View",
    "city": "Nurfiupu",
    "state": "ID",
    "zip": "89319"
  },
  "contact": {
    "phone": "(500) 920-2424",
    "servicePhone": "800667788"
  },
  "birthday": "1973-06-30T04:48:09.590Z",
  "ip": "246.184.43.106",
  "foo": "bar",
  "profile": {
    "about": "Gukki nir neselve tipsi vihso ti diwjeit ramib liwiro teabep wezwo wiw nu hog vuvad osuluwga. Akigapuj hakhotle gu paivec zi foobag tu ledwiuji eclo nidle mi gerrage ori kofhe ob. Sagti wuk zahebmej ukeku fav ahlig ki zisegud remojnih dokivo emutaku bih siba vikji. Wa bicgapot fuhu cek zawiit izatad zec buge konrebu otusikzaw riz tamzebo pucipa hima. Dijfofjot pe ideosu homjutu for kefe pijsir buicofov ojecilec ukobusas okebez du. Okan kubko ignawu pu bad popo vube totjazvad wuwki guvhuwfa ow gale pasubfi ful. De newwe nu wisadoc ter iz nedpaf sik da gaolori erovur ru sato fo iwasew kujufa.",
    "bio": "Degodi oregigif ge mon gaja jeanco wuc hihal ke dium wam omu capezvek hob mugik zita ufuuje. Iba rejgisfi dom tafpihde rorzar amavu wognaze kalzudel udatosuso lo ladca sizigu cena cih tummij rif murrumi kuika. Rif lav sure giar nekgu afoves gaavuzod miphutef mis bulgis ipfucip ise na jucha doridzo wimlezad vilrefeh ni. Guwukiv tigu soup atkibje cuav sowu so wa pu bos vegwi loj. Vijow tunkulciz kijuz gumus vilol ursu kupim vopguk bace volweces ve jone peubjim mel. Jolarlub wi manemge riwgag ewisub zus golapudu fab hec so bidokke ku fibu."
  },
  "apiKey": "b787c26f0862d83e4bb84737e52e45b63e8dc55083d22596abdba06fb1380c89",
  "currency": {
    "code": "IRR",
    "name": "Iran Rial"
  }
}